resultr_plot/__init__.py
resultr_plot-0.1.2.dist-info/METADATA
resultr_plot-0.1.2.dist-info/RECORD
resultr_plot-0.1.2.dist-info/WHEEL
resultr_plot-0.1.2.dist-info/top_level.txt
