Metadata-Version: 2.1
Name: resultr-plot
Version: 0.1.2
Summary: Making UCL PHAS results better
Home-page: https://github.com/haykkh/resultr-plot
Author: Hayk Khachatryan
Author-email: hi@hayk.io
License: MIT
Platform: UNKNOWN
Classifier: Programming Language :: Python :: 3
Classifier: License :: OSI Approved :: MIT License
Classifier: Operating System :: OS Independent
Requires-Dist: inquirer (>=2.2.0)
Requires-Dist: pandas (>=0.23.0)
Requires-Dist: matplotlib (>=2.2.2)
